{
  "preRequisiteTypes:7": [
    0,
    2
  ],
  "preRequisites:11": [
    1466692388,
    857979572
  ],
  "properties:10": {
    "betterquesting:10": {
      "desc:8": "可以的话不要尝试它，除非你喜欢完全遵守格雷科技的世界观建设你的基地。",
      "frame:8": "HEXAGON90",
      "icon:10": {
        "Count:3": 1,
        "Damage:2": 16,
        "id:8": "gregtech:mte"
      },
      "name:8": "§8更好的蒸汽熔炉"
    }
  },
  "questID:3": 633827744,
  "rewards:9": {
    "0:10": {
      "choices:9": {
        "0:10": {
          "Count:3": 2,
          "Damage:2": 2,
          "id:8": "morefurnaces:furnaceblock"
        },
        "1:10": {
          "Count:3": 2,
          "Damage:2": 3,
          "id:8": "morefurnaces:furnaceblock"
        }
      },
      "index:3": 0,
      "rewardID:8": "bq_standard:choice"
    }
  },
  "tasks:9": {
    "0:10": {
      "index:3": 0,
      "requiredItems:9": {
        "0:10": {
          "Count:3": 1,
          "Damage:2": 16,
          "id:8": "gregtech:mte"
        }
      },
      "taskID:8": "bq_standard:retrieval"
    }
  }
}