{
  "preRequisiteTypes:7": [
    2
  ],
  "preRequisites:11": [
    1738168220
  ],
  "properties:10": {
    "betterquesting:10": {
      "desc:8": "相信我，做一台粉碎机会比你拿研钵手搓粉末好得多！\n\n§3它稍微有点慢......",
      "frame:8": "HEXAGON90",
      "icon:10": {
        "Count:3": 1,
        "Damage:2": 9,
        "id:8": "gregtech:mte"
      },
      "name:8": "§a粉碎机 1.0"
    }
  },
  "questID:3": 8409593,
  "tasks:9": {
    "0:10": {
      "index:3": 0,
      "requiredItems:9": {
        "0:10": {
          "Count:3": 1,
          "Damage:2": 9,
          "id:8": "gregtech:mte"
        }
      },
      "taskID:8": "bq_standard:retrieval"
    }
  }
}